kidshell/__init__.py
kidshell/__main__.py
kidshell/cli/__init__.py
kidshell/cli/__main__.py
kidshell/cli/config_command.py
kidshell/cli/main.py
kidshell/cli/rich_ui.py
kidshell/cli/sandbox.py
kidshell/cli/web.py
kidshell/core/__init__.py
kidshell/core/config.py
kidshell/core/engine.py
kidshell/core/handlers/__init__.py
kidshell/core/handlers/base.py
kidshell/core/handlers/colors.py
kidshell/core/handlers/emoji.py
kidshell/core/handlers/loops.py
kidshell/core/handlers/math.py
kidshell/core/handlers/number_tree.py
kidshell/core/handlers/quiz.py
kidshell/core/handlers/symbols.py
kidshell/core/i18n.py
kidshell/core/models/__init__.py
kidshell/core/models/achievements.py
kidshell/core/models/session.py
kidshell/core/safe_math.py
kidshell/core/services/__init__.py
kidshell/core/services/data_service.py
kidshell/core/services/quiz_service.py
kidshell/core/types.py
kidshell/frontends/__init__.py
kidshell/frontends/terminal/__init__.py
kidshell/frontends/terminal/app.py
kidshell/frontends/textual_app/__init__.py
kidshell/frontends/textual_app/app.py
kidshell-0.1.0a0.dist-info/WHEEL
kidshell-0.1.0a0.dist-info/entry_points.txt
kidshell-0.1.0a0.dist-info/METADATA
kidshell-0.1.0a0.dist-info/RECORD
