Metadata-Version: 2.3
Name: kidshell
Version: 0.1.0a0
Summary: A REPL shell that is resilient in the face of childish expectations
Keywords: repl,shell,education,children,interactive,learning
Author: Anthony Wu
Author-email: Anthony Wu <ls-file-gh-issue@users.noreply.github.com>
License: MIT
Classifier: Development Status :: 4 - Beta
Classifier: Environment :: Console
Classifier: Intended Audience :: Education
Classifier: License :: OSI Approved :: MIT License
Classifier: Operating System :: OS Independent
Classifier: Programming Language :: Python
Classifier: Programming Language :: Python :: 3
Classifier: Programming Language :: Python :: 3.9
Classifier: Programming Language :: Python :: 3.10
Classifier: Programming Language :: Python :: 3.11
Classifier: Programming Language :: Python :: 3.12
Classifier: Programming Language :: Python :: 3.13
Classifier: Programming Language :: Python :: 3.14
Classifier: Programming Language :: Python :: 3 :: Only
Classifier: Topic :: Education
Classifier: Topic :: Software Development :: Libraries :: Python Modules
Requires-Dist: platformdirs>=4.3.6
Requires-Dist: requests>=2.27.1,<3.0
Requires-Dist: rich==14.1.0
Requires-Dist: scipy>=1.9,<2.0
Requires-Dist: sympy>=1.11,<2.0
Requires-Dist: textualize>=0.1,<1.0
Requires-Dist: tqdm>4.60,<5.0
Requires-Dist: typing-extensions>=3.7.4,<5.0 ; python_full_version < '3.10'
Requires-Python: >=3.9
Project-URL: Changelog, https://github.com/anthonywu/kidshell/blob/main/CHANGELOG.md
Project-URL: Issues, https://github.com/anthonywu/kidshell/issues
Project-URL: Repository, https://github.com/anthonywu/kidshell
